pytsecr/__init__.py
pytsecr/setup.py
pytsecr/src.py
pytsecr-0.1.dist-info/METADATA
pytsecr-0.1.dist-info/WHEEL
pytsecr-0.1.dist-info/top_level.txt
pytsecr-0.1.dist-info/RECORD
